annopro/__init__.py
annopro/__main__.py
annopro/_version.py
annopro/prediction.py
annopro/resources.py
annopro/data_procession/__init__.py
annopro/data_procession/data_predict.py
annopro/data_procession/utils.py
annopro/focal_loss/__init__.py
annopro/focal_loss/_binary_focal_loss.py
annopro/focal_loss/_categorical_focal_loss.py
annopro/focal_loss/utils/__init__.py
annopro/focal_loss/utils/validation.py
annopro-0.2.dist-info/LICENSE
annopro-0.2.dist-info/METADATA
annopro-0.2.dist-info/WHEEL
annopro-0.2.dist-info/entry_points.txt
annopro-0.2.dist-info/top_level.txt
annopro-0.2.dist-info/RECORD
