Metadata-Version: 2.1
Name: annopro
Version: 0.2
Summary: A simple python package for annotating protein sequences
Author-email: "Zheng.L.Y" <zhenglingyan@zju.edu.cn>, "Zhang.H.N" <zhang.h.n@foxmail.com>
License: MIT
Project-URL: Homepage, https://github.com/idrblab/AnnoPRO
Project-URL: Bug Tracker, https://github.com/idrblab/AnnoPRO/issues
Classifier: Programming Language :: Python :: 3
Classifier: License :: OSI Approved :: MIT License
Classifier: Operating System :: OS Independent
Classifier: Topic :: Scientific/Engineering :: Bio-Informatics
Classifier: Environment :: Console
Requires-Python: >=3.8
License-File: LICENSE
Requires-Dist: llvmlite (>=0.38.1)
Requires-Dist: numpy (<=1.19.5)
Requires-Dist: pandas (<=1.4.8,>=1.2.4)
Requires-Dist: scikit-learn (>=1.0.2)
Requires-Dist: scipy (<=1.9.5,>=1.4.1)
Requires-Dist: tensorflow (<=2.6.5,>=2.5.0)
Requires-Dist: threadpoolctl (>=3.1.0)
Requires-Dist: fasta (>=2.3.2)
Requires-Dist: wget
Requires-Dist: diamond4py (>=0.0.2rc2)
Requires-Dist: profeatpy (>=0.0.2)
